MANIFEST.in
README.rst
pytest.ini
setup.py
tox.ini
pyramid_admin2/__init__.py
pyramid_admin2/action_conf.py
pyramid_admin2/admin_manager.py
pyramid_admin2/helpers.py
pyramid_admin2/model.py
pyramid_admin2/resources.py
pyramid_admin2/view_config.py
pyramid_admin2.egg-info/PKG-INFO
pyramid_admin2.egg-info/SOURCES.txt
pyramid_admin2.egg-info/dependency_links.txt
pyramid_admin2.egg-info/not-zip-safe
pyramid_admin2.egg-info/requires.txt
pyramid_admin2.egg-info/top_level.txt
pyramid_admin2/templates/_layout.mak
pyramid_admin2/templates/create.mak
pyramid_admin2/templates/detail.mak
pyramid_admin2/templates/index.mak
pyramid_admin2/templates/list.mak
pyramid_admin2/templates/no_schema.mak
pyramid_admin2/templates/paging_panel.mak
pyramid_admin2/templates/update.mak
pyramid_admin2/views/__init__.py
pyramid_admin2/views/model_view.py
pyramid_admin2/views/paging_panel.py