Metadata-Version: 1.1
Name: pyramid-admin2
Version: 0.2
Summary: pyramid_admin2
Home-page: https://github.com/tarzanjw/pyramid_admin2
Author: Hoc .T Do
Author-email: hoc3010@gmail.com
License: UNKNOWN
Keywords: web wsgi bfg pylons pyramid
Platform: UNKNOWN
Classifier: Programming Language :: Python
Classifier: Framework :: Pyramid
Classifier: Topic :: Internet :: WWW/HTTP
Classifier: Topic :: Internet :: WWW/HTTP :: WSGI :: Application
